jid/__init__.py
jid/__manifest__.py
jid/models/__init__.py
jid/models/res_partner.py
jid/static/description/icon.png
jid/static/description/icon.svg
jid/static/description/index.html
jid/static/description/logo.png
jid/static/description/logo.svg
jid/views/res_partner_views.xml
odoo_jid-0.0.1.dist-info/LICENSE
odoo_jid-0.0.1.dist-info/METADATA
odoo_jid-0.0.1.dist-info/WHEEL
odoo_jid-0.0.1.dist-info/RECORD
